<?xml version="1.0" encoding="utf-8" ?>
<dwsync>
<file name="jquery.1.11.1.js" server="ftp.intrap.ca" local="130843465260000000" remote="130908963000000000" Dst="1" />
<file name="bootstrap.js" server="ftp.intrap.ca" local="130898427796757675" remote="130908963000000000" Dst="1" />
<file name="SmoothScroll.js" server="ftp.intrap.ca" local="130666803840000000" remote="130908963000000000" Dst="1" />
<file name="jquery.prettyPhoto.js" server="ftp.intrap.ca" local="130603315920000000" remote="130908963000000000" Dst="1" />
<file name="jquery.isotope.js" server="ftp.intrap.ca" local="130626466720000000" remote="130908963000000000" Dst="1" />
<file name="jquery.counterup.js" server="ftp.intrap.ca" local="130845997140000000" remote="130908963000000000" Dst="1" />
<file name="waypoints.js" server="ftp.intrap.ca" local="130845997140000000" remote="130908963000000000" Dst="1" />
<file name="jqBootstrapValidation.js" server="ftp.intrap.ca" local="130591501820000000" remote="130908963000000000" Dst="1" />
<file name="contact_me.js" server="ftp.intrap.ca" local="130860771080000000" remote="130908963000000000" Dst="1" />
<file name="owl.carousel.js" server="ftp.intrap.ca" local="130455952040000000" remote="130908963000000000" Dst="1" />
<file name="logocontroller.js" server="ftp.intrap.ca" local="130906111311084801" remote="130908963000000000" Dst="1" />
<file name="main.js" server="ftp.intrap.ca" local="130906091040850896" remote="130908963000000000" Dst="1" />
</dwsync>